mcmststream/__init__.py
mcmststream/core.py
mcmststream/utils.py
mcmststream/data/ExclaStar.txt
mcmststream-1.0.4.dist-info/licenses/LICENSE
mcmststream-1.0.4.dist-info/METADATA
mcmststream-1.0.4.dist-info/WHEEL
mcmststream-1.0.4.dist-info/top_level.txt
mcmststream-1.0.4.dist-info/RECORD
